clappy.py
clappy-1.0.4.dist-info/LICENSE
clappy-1.0.4.dist-info/METADATA
clappy-1.0.4.dist-info/WHEEL
clappy-1.0.4.dist-info/top_level.txt
clappy-1.0.4.dist-info/RECORD
