Metadata-Version: 2.1
Name: clappy
Version: 1.0.4
Summary: Command line argument parser for pythonic code
Home-page: https://github.com/yoko72/clappy
Author: Toshiyuki Yokoyama
Author-email: yokoyamacode@gmail.com
License: UNKNOWN
Keywords: command line,argument,option,parser
Platform: UNKNOWN
Classifier: Topic :: Software Development :: Libraries :: Python Modules
Requires-Python: !=3.0.*,!=3.1.*,>=2.7
License-File: LICENSE
